{
  "date": "2026-02-27",
  "projects": {
    "shadcn-admin-kit-main (Workspace)": {
      "totalLinesAdded": 209,
      "totalLinesRemoved": 5,
      "totalActiveTime": 21,
      "files": {
        "c:\\Users\\jaden.black\\alignsynch.com\\mono-apps\\shadcn-admin-kit-main\\.vscode\\extensions.json": [
          {
            "timestamp": "2026-02-27T03:30:33.682Z",
            "fileName": "c:\\Users\\jaden.black\\alignsynch.com\\mono-apps\\shadcn-admin-kit-main\\.vscode\\extensions.json",
            "fileType": ".json",
            "linesAdded": 8,
            "linesRemoved": 0,
            "projectName": "shadcn-admin-kit-main (Workspace)",
            "content": {
              "added": [],
              "removed": []
            },
            "duration": 0,
            "language": "json"
          },
          {
            "timestamp": "2026-02-27T03:30:33.996Z",
            "fileName": "c:\\Users\\jaden.black\\alignsynch.com\\mono-apps\\shadcn-admin-kit-main\\.vscode\\extensions.json",
            "fileType": ".json",
            "linesAdded": 1,
            "linesRemoved": 0,
            "projectName": "shadcn-admin-kit-main (Workspace)",
            "content": {
              "added": [],
              "removed": []
            },
            "duration": 1,
            "language": "json"
          },
          {
            "timestamp": "2026-02-27T03:32:01.159Z",
            "fileName": "c:\\Users\\jaden.black\\alignsynch.com\\mono-apps\\shadcn-admin-kit-main\\.vscode\\extensions.json",
            "fileType": ".json",
            "linesAdded": 0,
            "linesRemoved": 1,
            "projectName": "shadcn-admin-kit-main (Workspace)",
            "content": {
              "added": [],
              "removed": []
            },
            "duration": 2,
            "language": "json"
          }
        ],
        "c:\\Users\\jaden.black\\alignsynch.com\\mono-apps\\shadcn-admin-kit-main\\shadcn-admin-kit-main.code-workspace": [
          {
            "timestamp": "2026-02-27T03:30:34.013Z",
            "fileName": "c:\\Users\\jaden.black\\alignsynch.com\\mono-apps\\shadcn-admin-kit-main\\shadcn-admin-kit-main.code-workspace",
            "fileType": ".code-workspace",
            "linesAdded": 26,
            "linesRemoved": 0,
            "projectName": "shadcn-admin-kit-main (Workspace)",
            "content": {
              "added": [],
              "removed": []
            },
            "duration": 1,
            "language": "code-workspace"
          },
          {
            "timestamp": "2026-02-27T03:32:01.262Z",
            "fileName": "c:\\Users\\jaden.black\\alignsynch.com\\mono-apps\\shadcn-admin-kit-main\\shadcn-admin-kit-main.code-workspace",
            "fileType": ".code-workspace",
            "linesAdded": 0,
            "linesRemoved": 1,
            "projectName": "shadcn-admin-kit-main (Workspace)",
            "content": {
              "added": [],
              "removed": []
            },
            "duration": 2,
            "language": "code-workspace"
          }
        ],
        "c:\\Users\\jaden.black\\AppData\\Roaming\\Antigravity\\User\\settings.json": [
          {
            "timestamp": "2026-02-27T04:14:09.373Z",
            "fileName": "c:\\Users\\jaden.black\\AppData\\Roaming\\Antigravity\\User\\settings.json",
            "fileType": ".json",
            "linesAdded": 61,
            "linesRemoved": 0,
            "projectName": "shadcn-admin-kit-main (Workspace)",
            "content": {
              "added": [],
              "removed": []
            },
            "duration": 0,
            "language": "json"
          },
          {
            "timestamp": "2026-02-27T04:14:09.535Z",
            "fileName": "c:\\Users\\jaden.black\\AppData\\Roaming\\Antigravity\\User\\settings.json",
            "fileType": ".json",
            "linesAdded": 3,
            "linesRemoved": 0,
            "projectName": "shadcn-admin-kit-main (Workspace)",
            "content": {
              "added": [],
              "removed": []
            },
            "duration": 1,
            "language": "json"
          },
          {
            "timestamp": "2026-02-27T04:14:13.328Z",
            "fileName": "c:\\Users\\jaden.black\\AppData\\Roaming\\Antigravity\\User\\settings.json",
            "fileType": ".json",
            "linesAdded": 1,
            "linesRemoved": 0,
            "projectName": "shadcn-admin-kit-main (Workspace)",
            "content": {
              "added": [],
              "removed": []
            },
            "duration": 1,
            "language": "json"
          },
          {
            "timestamp": "2026-02-27T04:14:23.504Z",
            "fileName": "c:\\Users\\jaden.black\\AppData\\Roaming\\Antigravity\\User\\settings.json",
            "fileType": ".json",
            "linesAdded": 1,
            "linesRemoved": 0,
            "projectName": "shadcn-admin-kit-main (Workspace)",
            "content": {
              "added": [],
              "removed": []
            },
            "duration": 1,
            "language": "json"
          },
          {
            "timestamp": "2026-02-27T04:14:42.790Z",
            "fileName": "c:\\Users\\jaden.black\\AppData\\Roaming\\Antigravity\\User\\settings.json",
            "fileType": ".json",
            "linesAdded": 1,
            "linesRemoved": 0,
            "projectName": "shadcn-admin-kit-main (Workspace)",
            "content": {
              "added": [],
              "removed": []
            },
            "duration": 1,
            "language": "json"
          },
          {
            "timestamp": "2026-02-27T04:14:42.802Z",
            "fileName": "c:\\Users\\jaden.black\\AppData\\Roaming\\Antigravity\\User\\settings.json",
            "fileType": ".json",
            "linesAdded": 1,
            "linesRemoved": 0,
            "projectName": "shadcn-admin-kit-main (Workspace)",
            "content": {
              "added": [],
              "removed": []
            },
            "duration": 1,
            "language": "json"
          },
          {
            "timestamp": "2026-02-27T04:14:43.650Z",
            "fileName": "c:\\Users\\jaden.black\\AppData\\Roaming\\Antigravity\\User\\settings.json",
            "fileType": ".json",
            "linesAdded": 1,
            "linesRemoved": 0,
            "projectName": "shadcn-admin-kit-main (Workspace)",
            "content": {
              "added": [],
              "removed": []
            },
            "duration": 1,
            "language": "json"
          },
          {
            "timestamp": "2026-02-27T04:14:46.076Z",
            "fileName": "c:\\Users\\jaden.black\\AppData\\Roaming\\Antigravity\\User\\settings.json",
            "fileType": ".json",
            "linesAdded": 1,
            "linesRemoved": 0,
            "projectName": "shadcn-admin-kit-main (Workspace)",
            "content": {
              "added": [],
              "removed": []
            },
            "duration": 1,
            "language": "json"
          },
          {
            "timestamp": "2026-02-27T04:14:46.692Z",
            "fileName": "c:\\Users\\jaden.black\\AppData\\Roaming\\Antigravity\\User\\settings.json",
            "fileType": ".json",
            "linesAdded": 3,
            "linesRemoved": 0,
            "projectName": "shadcn-admin-kit-main (Workspace)",
            "content": {
              "added": [],
              "removed": []
            },
            "duration": 1,
            "language": "json"
          },
          {
            "timestamp": "2026-02-27T04:14:47.409Z",
            "fileName": "c:\\Users\\jaden.black\\AppData\\Roaming\\Antigravity\\User\\settings.json",
            "fileType": ".json",
            "linesAdded": 0,
            "linesRemoved": 3,
            "projectName": "shadcn-admin-kit-main (Workspace)",
            "content": {
              "added": [],
              "removed": []
            },
            "duration": 1,
            "language": "json"
          },
          {
            "timestamp": "2026-02-27T04:14:50.092Z",
            "fileName": "c:\\Users\\jaden.black\\AppData\\Roaming\\Antigravity\\User\\settings.json",
            "fileType": ".json",
            "linesAdded": 1,
            "linesRemoved": 0,
            "projectName": "shadcn-admin-kit-main (Workspace)",
            "content": {
              "added": [],
              "removed": []
            },
            "duration": 1,
            "language": "json"
          },
          {
            "timestamp": "2026-02-27T04:14:57.827Z",
            "fileName": "c:\\Users\\jaden.black\\AppData\\Roaming\\Antigravity\\User\\settings.json",
            "fileType": ".json",
            "linesAdded": 1,
            "linesRemoved": 0,
            "projectName": "shadcn-admin-kit-main (Workspace)",
            "content": {
              "added": [],
              "removed": []
            },
            "duration": 1,
            "language": "json"
          },
          {
            "timestamp": "2026-02-27T04:15:03.964Z",
            "fileName": "c:\\Users\\jaden.black\\AppData\\Roaming\\Antigravity\\User\\settings.json",
            "fileType": ".json",
            "linesAdded": 1,
            "linesRemoved": 0,
            "projectName": "shadcn-admin-kit-main (Workspace)",
            "content": {
              "added": [],
              "removed": []
            },
            "duration": 1,
            "language": "json"
          }
        ],
        "c:\\Users\\jaden.black\\alignsynch.com\\mono-apps\\shadcn-admin-kit-main\\shadcn-extension.json": [
          {
            "timestamp": "2026-02-27T06:22:44.431Z",
            "fileName": "c:\\Users\\jaden.black\\alignsynch.com\\mono-apps\\shadcn-admin-kit-main\\shadcn-extension.json",
            "fileType": ".json",
            "linesAdded": 3,
            "linesRemoved": 0,
            "projectName": "shadcn-admin-kit-main (Workspace)",
            "content": {
              "added": [],
              "removed": []
            },
            "duration": 0,
            "language": "json"
          },
          {
            "timestamp": "2026-02-27T06:22:50.331Z",
            "fileName": "c:\\Users\\jaden.black\\alignsynch.com\\mono-apps\\shadcn-admin-kit-main\\shadcn-extension.json",
            "fileType": ".json",
            "linesAdded": 1,
            "linesRemoved": 0,
            "projectName": "shadcn-admin-kit-main (Workspace)",
            "content": {
              "added": [],
              "removed": []
            },
            "duration": 1,
            "language": "json"
          }
        ],
        "c:\\Users\\jaden.black\\.gemini\\antigravity\\brain\\5d74860f-dce5-4941-a669-1e5f6a2a9242\\implementation_plan.md.resolved": [
          {
            "timestamp": "2026-02-27T07:09:08.722Z",
            "fileName": "c:\\Users\\jaden.black\\.gemini\\antigravity\\brain\\5d74860f-dce5-4941-a669-1e5f6a2a9242\\implementation_plan.md.resolved",
            "fileType": ".resolved",
            "linesAdded": 79,
            "linesRemoved": 0,
            "projectName": "shadcn-admin-kit-main (Workspace)",
            "content": {
              "added": [],
              "removed": []
            },
            "duration": 0,
            "language": "resolved"
          }
        ],
        "c:\\Users\\jaden.black\\.gemini\\antigravity\\brain\\5d74860f-dce5-4941-a669-1e5f6a2a9242\\task.md": [
          {
            "timestamp": "2026-02-27T07:10:37.218Z",
            "fileName": "c:\\Users\\jaden.black\\.gemini\\antigravity\\brain\\5d74860f-dce5-4941-a669-1e5f6a2a9242\\task.md",
            "fileType": ".md",
            "linesAdded": 15,
            "linesRemoved": 0,
            "projectName": "shadcn-admin-kit-main (Workspace)",
            "content": {
              "added": [],
              "removed": []
            },
            "duration": 2,
            "language": "md"
          }
        ]
      },
      "languageStats": {
        "json": 3,
        "code-workspace": 3
      },
      "changeFrequency": {
        "0": 6
      },
      "topFiles": [
        "c:\\Users\\jaden.black\\alignsynch.com\\mono-apps\\shadcn-admin-kit-main\\.vscode\\extensions.json",
        "c:\\Users\\jaden.black\\alignsynch.com\\mono-apps\\shadcn-admin-kit-main\\shadcn-admin-kit-main.code-workspace"
      ],
      "averageChangeSize": 7.4
    }
  },
  "totalActiveTime": 5,
  "totalProjects": 1,
  "totalFiles": 2,
  "mostActiveHours": [
    0
  ],
  "mostUsedLanguages": [
    "json",
    "code-workspace"
  ]
}